tacotron/__init__.py
tacotron/cmudict-0.7b.txt
tacotron/config.toml
tacotron/dataset.py
tacotron/model.py
tacotron/text.py
tacotron-0.1.1.dist-info/LICENSE
tacotron-0.1.1.dist-info/METADATA
tacotron-0.1.1.dist-info/WHEEL
tacotron-0.1.1.dist-info/top_level.txt
tacotron-0.1.1.dist-info/RECORD
