Metadata-Version: 2.1
Name: tacotron
Version: 0.1.1
Summary: A PyTorch implementation of Location-Relative Attention Mechanisms For Robust Long-Form Speech Synthesis.
Home-page: https://github.com/bshall/Tacotron
Author: Benjamin van Niekerk
Author-email: benjamin.l.van.niekerk@gmail.com
License: UNKNOWN
Project-URL: Source, https://github.com/bshall/Tacotron
Project-URL: Samples, https://bshall.github.io/tacotron/
Keywords: Speech Synthesis,Tacotron,Text-to-Speech,PyTorch
Platform: UNKNOWN
Classifier: Natural Language :: English
Classifier: Intended Audience :: Science/Research
Classifier: License :: OSI Approved :: MIT License
Classifier: Operating System :: POSIX :: Linux
Classifier: Programming Language :: Python
Classifier: Programming Language :: Python :: 3.6
Classifier: Programming Language :: Python :: 3.7
Classifier: Programming Language :: Python :: 3.8
Classifier: Programming Language :: Python :: 3.9
Classifier: Topic :: Scientific/Engineering
Classifier: Topic :: Scientific/Engineering :: Artificial Intelligence
Requires-Python: >=3.6
Requires-Dist: librosa (>=0.8.0)
Requires-Dist: numpy (>=1.18.0)
Requires-Dist: tqdm (>=4.41)
Requires-Dist: requests
Requires-Dist: importlib-resources
Requires-Dist: toml (>=0.10.2)
